cloudforet/__init__.py
cloudforet/search/__init__.py
cloudforet/search/conf/__init__.py
cloudforet/search/conf/global_conf.py
cloudforet/search/interface/__init__.py
cloudforet/search/interface/grpc/__init__.py
cloudforet/search/interface/grpc/resource.py
cloudforet/search/lib/__init__.py
cloudforet/search/lib/pymongo_client.py
cloudforet/search/manager/__init__.py
cloudforet/search/manager/identity_manager.py
cloudforet/search/manager/resource_manager.py
cloudforet/search/model/__init__.py
cloudforet/search/model/resource/__init__.py
cloudforet/search/model/resource/request.py
cloudforet/search/model/resource/response.py
cloudforet/search/service/__init__.py
cloudforet/search/service/resource.py
cloudforet_search-0.0.1.dist-info/METADATA
cloudforet_search-0.0.1.dist-info/WHEEL
cloudforet_search-0.0.1.dist-info/top_level.txt
cloudforet_search-0.0.1.dist-info/RECORD
