Metadata-Version: 2.1
Name: cloudforet-search
Version: 0.0.1
Summary: Cloudforet search service
Home-page: https://cloudforet.io/
Author: Cloudforet Admin
Author-email: admin@cloudforet.io
License: Apache License 2.0
Platform: UNKNOWN
Requires-Dist: spaceone-core
Requires-Dist: spaceone-api
Requires-Dist: pymongo
